torchok/__init__.py
torchok/__main__.py
torchok/callbacks/__init__.py
torchok/callbacks/checkpoint_onnx.py
torchok/callbacks/finalize_logger.py
torchok/callbacks/freeze_unfreeze.py
torchok/constructor/__init__.py
torchok/constructor/auto_lr_find.py
torchok/constructor/config_structure.py
torchok/constructor/constructor.py
torchok/constructor/load.py
torchok/constructor/logger.py
torchok/constructor/registry.py
torchok/constructor/runner.py
torchok/data/__init__.py
torchok/data/datasets/__init__.py
torchok/data/datasets/base.py
torchok/data/datasets/classification/__init__.py
torchok/data/datasets/classification/classification.py
torchok/data/datasets/detection/__init__.py
torchok/data/datasets/detection/detection.py
torchok/data/datasets/examples/__init__.py
torchok/data/datasets/examples/cifar10.py
torchok/data/datasets/examples/coco_detection.py
torchok/data/datasets/examples/coco_segmentation.py
torchok/data/datasets/examples/sop.py
torchok/data/datasets/examples/sweet_pepper.py
torchok/data/datasets/examples/triplet_sop.py
torchok/data/datasets/representation/__init__.py
torchok/data/datasets/representation/unsupervised_contrastive_dataset.py
torchok/data/datasets/representation/validation.py
torchok/data/datasets/segmentation/__init__.py
torchok/data/datasets/segmentation/image_segmentation.py
torchok/data/transforms/__init__.py
torchok/data/transforms/pixelwise.py
torchok/data/transforms/spatial.py
torchok/data/transforms/utils.py
torchok/losses/__init__.py
torchok/losses/base.py
torchok/losses/classification/__init__.py
torchok/losses/classification/binary_cross_entropy.py
torchok/losses/detection/__init__.py
torchok/losses/detection/mmdet_losses.py
torchok/losses/representation/__init__.py
torchok/losses/representation/pairwise.py
torchok/losses/segmentation/__init__.py
torchok/losses/segmentation/dice.py
torchok/metrics/__init__.py
torchok/metrics/detection.py
torchok/metrics/index_base_metric.py
torchok/metrics/metrics_manager.py
torchok-0.4.12.dist-info/METADATA
torchok-0.4.12.dist-info/LICENSE
torchok-0.4.12.dist-info/WHEEL
torchok-0.4.12.dist-info/RECORD
