Metadata-Version: 2.1
Name: torchok
Version: 0.4.12
Summary: The toolkit for fast Deep Learning experiments in Computer Vision
Home-page: https://github.com/eora-ai/torchok
License: Apache-2.0
Keywords: Computer Vision,Deep Learning,Neural Networks
Author: Vlad Vinogradov
Author-email: vladvin@eora.ai
Requires-Python: >=3.7,<3.11
Classifier: Development Status :: 3 - Alpha
Classifier: Intended Audience :: Developers
Classifier: Intended Audience :: Science/Research
Classifier: License :: OSI Approved :: Apache Software License
Classifier: Programming Language :: Python :: 3
Classifier: Programming Language :: Python :: 3.7
Classifier: Programming Language :: Python :: 3.8
Classifier: Programming Language :: Python :: 3.9
Classifier: Programming Language :: Python :: 3.10
Classifier: Topic :: Scientific/Engineering :: Artificial Intelligence
Requires-Dist: albumentations (==1.3.0)
Requires-Dist: faiss-cpu (==1.7.2)
Requires-Dist: hydra-core (>=1.2,<1.3)
Requires-Dist: mmdet (==2.26.0)
Requires-Dist: numpy (>=1.21,<1.22) ; python_full_version >= "3.7.1" and python_version < "3.8"
Requires-Dist: numpy (>=1.22,<1.23) ; python_version >= "3.8" and python_version < "3.11"
Requires-Dist: onnx (>=1.12,<1.13)
Requires-Dist: onnxruntime-gpu (>=1.12,<1.13)
Requires-Dist: opencv-python (>=4.6,<4.7)
Requires-Dist: pandas (>=1.3,<1.4) ; python_full_version >= "3.7.1" and python_version < "3.8"
Requires-Dist: pandas (>=1.4,<1.5) ; python_version >= "3.8" and python_version < "3.11"
Requires-Dist: parameterized (>=0.8,<0.9)
Requires-Dist: pillow (>=9.1,<9.2)
Requires-Dist: pytorch-lightning (==1.8.4.post0)
Requires-Dist: ranx (>=0.2,<0.3)
Requires-Dist: timm (>=0.6,<0.7)
Requires-Dist: torch (==1.12.1)
Requires-Dist: torchmetrics (>=0.11,<0.12)
Requires-Dist: torchvision (==0.13.1)
Project-URL: Documentation, https://torchok.readthedocs.io/
